waldur_auth_saml2/__init__.py
waldur_auth_saml2/admin.py
waldur_auth_saml2/apps.py
waldur_auth_saml2/extension.py
waldur_auth_saml2/filters.py
waldur_auth_saml2/handlers.py
waldur_auth_saml2/log.py
waldur_auth_saml2/models.py
waldur_auth_saml2/serializers.py
waldur_auth_saml2/tasks.py
waldur_auth_saml2/urls.py
waldur_auth_saml2/utils.py
waldur_auth_saml2/views.py
waldur_auth_saml2/management/__init__.py
waldur_auth_saml2/management/commands/__init__.py
waldur_auth_saml2/management/commands/sync_saml2_providers.py
waldur_auth_saml2/migrations/0001_initial.py
waldur_auth_saml2/migrations/__init__.py
waldur_auth_saml2-0.8.2.dist-info/DESCRIPTION.rst
waldur_auth_saml2-0.8.2.dist-info/METADATA
waldur_auth_saml2-0.8.2.dist-info/RECORD
waldur_auth_saml2-0.8.2.dist-info/WHEEL
waldur_auth_saml2-0.8.2.dist-info/entry_points.txt
waldur_auth_saml2-0.8.2.dist-info/metadata.json
waldur_auth_saml2-0.8.2.dist-info/top_level.txt
